multildap/__init__.py
multildap/attr_rewrite.py
multildap/client.py
multildap/commands.py
multildap/decorators.py
multildap/multildapd.py
multildap/satosa/multiple_ldap_attribute_store.py
multildap-0.3.data/scripts/multildapd.py
multildap-0.3.dist-info/AUTHORS
multildap-0.3.dist-info/LICENSE
multildap-0.3.dist-info/METADATA
multildap-0.3.dist-info/WHEEL
multildap-0.3.dist-info/top_level.txt
multildap-0.3.dist-info/RECORD
