Metadata-Version: 2.1
Name: multildap
Version: 0.3
Summary: LDAP client or proxy to multiple LDAP server
Home-page: https://github.com/peppelinux/multildap
Author: Giuseppe De Marco
Author-email: giuseppe.demarco@unical.it
License: BSD
Platform: UNKNOWN
Classifier: Development Status :: 5 - Production/Stable
Classifier: License :: OSI Approved :: BSD License
Classifier: Programming Language :: Python :: 2
Classifier: Programming Language :: Python :: 3
Requires-Dist: ldap3
Requires-Dist: gevent
